LICENSE
MANIFEST.in
README.rst
setup.py
cachetree/__init__.py
cachetree/auth.py
cachetree/cache.py
cachetree/exceptions.py
cachetree/invalidation.py
cachetree/manager.py
cachetree/middleware.py
cachetree/models.py
cachetree/settings.py
cachetree/shortcuts.py
cachetree/tests.py
cachetree/utils.py
cachetree/fixtures/testdata.json
django_cachetree.egg-info/PKG-INFO
django_cachetree.egg-info/SOURCES.txt
django_cachetree.egg-info/dependency_links.txt
django_cachetree.egg-info/requires.txt
django_cachetree.egg-info/top_level.txt