Metadata-Version: 1.1
Name: django-cachetree
Version: 0.1.3
Summary: cache configurable trees of related model instances in Django
Home-page: https://github.com/brianjaystanley/django-cachetree
Author: Brian Jay Stanley
Author-email: brian@brianjaystanley.com
License: MIT
Keywords: django cache
Platform: UNKNOWN
Classifier: Development Status :: 4 - Beta
Classifier: Framework :: Django
Classifier: Intended Audience :: Developers
Classifier: License :: OSI Approved :: MIT License
Classifier: Operating System :: OS Independent
Classifier: Programming Language :: Python
Classifier: Topic :: Internet :: WWW/HTTP :: Dynamic Content
Classifier: Topic :: Software Development :: Libraries
Classifier: Topic :: Software Development :: Libraries :: Python Modules
